{"nodes":[{"id":"v1","t":"v","n":1,"x":"AND after this it came to pass, that David smote the Philistines, and subdued them: and David took Methegammah out of the hand of the Philistines."},{"id":"p_0","t":"p","src":"jst","lb":"JST: inspired_version_1867","x":"ND after this it came to pass that David .smote. the. Philistines, and subdue] them; and David took Metheg-ammah out. of the hand of"},{"id":"v2","t":"v","n":2,"x":"And he smote Moab, and measured them with a line, casting them down to the ground; even with two lines measured he to put to death, and with one full line to keep alive. And [so] the Moabites became…"},{"id":"v3","t":"v","n":3,"x":"David smote also Hadadezer, the son of Rehob, king of Zobah, as he went to recover his border at the river Euphrates."},{"id":"v4","t":"v","n":4,"x":"And David took from him a thousand [chariots], and seven hundred horsemen, and twenty thousand footmen: and David houghed all the chariot [horses], but reserved of them [for] an hundred chariots."},{"id":"v5","t":"v","n":5,"x":"And when the Syrians of Damascus came to succour Hadadezer king of Zobah, David slew of the Syrians two and twenty thousand men."},{"id":"v6","t":"v","n":6,"x":"Then David put garrisons in Syria of Damascus: and the Syrians became servants to David, [and] brought gifts. And the LORD preserved David whithersoever he went."},{"id":"v7","t":"v","n":7,"x":"And David took the shields of gold that were on the servants of Hadadezer, and brought them to Jerusalem."},{"id":"v8","t":"v","n":8,"x":"And from Betah, and from Berothai, cities of Hadadezer, king David took exceeding much brass."},{"id":"v9","t":"v","n":9,"x":"When Toi king of Hamath heard that David had smitten all the host of Hadadezer,"},{"id":"v10","t":"v","n":10,"x":"Then Toi sent Joram his son unto king David, to salute him, and to bless him, because he had"},{"id":"v11","t":"v","n":11,"x":"Which also king David did dedicate unto the LORD, with the silver and gold that he had dedicated of all nations which he subdued;"},{"id":"v12","t":"v","n":12,"x":"Of Syria, and of Moab, and of the children of Ammon, and of the Philistines, and of Amalek, and of the spoil of Hadadezer, son of Rehob, king of Zobah."},{"id":"v13","t":"v","n":13,"x":"And David gat [him] a name when he returned from smiting of the Syrians in the valley of salt, [being] eighteen thousand [men]."},{"id":"v14","t":"v","n":14,"x":"And he put garrisons in Edom; throughout all Edom put he garrisons, and all they of Edom became David's servants. And the LORD preserved David whithersoever he went."},{"id":"v15","t":"v","n":15,"x":"And David reigned over all Israel; and David executed judgment and justice unto all his people."},{"id":"v16","t":"v","n":16,"x":"And Joab the son of Zeruiah [was] over the host; and Jehoshaphat the son of Ahilud [was] recorder;"},{"id":"v17","t":"v","n":17,"x":"And Zadok the son of Ahitub, and Ahimelech the son of Abiathar, [were] the priests; and Seraiah [was] the scribe;"},{"id":"v18","t":"v","n":18,"x":"And Benaiah the son of Jehoiada [was over] both the Cherethites and the Pelethites; and David's sons were chief rulers."}],"edges":[{"s":"v1","t":"p_0","w":0.643},{"s":"v1","t":"p_0","w":0.519},{"s":"v1","t":"p_0","w":0.268},{"s":"v2","t":"p_0","w":0.816},{"s":"v2","t":"p_0","w":0.544},{"s":"v2","t":"p_0","w":0.516},{"s":"v3","t":"p_0","w":0.988},{"s":"v3","t":"p_0","w":0.397},{"s":"v3","t":"p_0","w":0.285},{"s":"v4","t":"p_0","w":1.0},{"s":"v4","t":"p_0","w":0.933},{"s":"v4","t":"p_0","w":0.256},{"s":"v5","t":"p_0","w":1.0},{"s":"v5","t":"p_0","w":0.578},{"s":"v6","t":"p_0","w":1.0},{"s":"v6","t":"p_0","w":0.833},{"s":"v6","t":"p_0","w":0.417},{"s":"v7","t":"p_0","w":1.0},{"s":"v7","t":"p_0","w":0.665},{"s":"v8","t":"p_0","w":1.0},{"s":"v9","t":"p_0","w":0.907},{"s":"v9","t":"p_0","w":0.686},{"s":"v10","t":"p_0","w":0.621},{"s":"v11","t":"p_0","w":0.831},{"s":"v11","t":"p_0","w":0.293},{"s":"v12","t":"p_0","w":0.963},{"s":"v12","t":"p_0","w":0.407},{"s":"v13","t":"p_0","w":0.923},{"s":"v14","t":"p_0","w":0.792},{"s":"v14","t":"p_0","w":0.708},{"s":"v14","t":"p_0","w":0.443},{"s":"v14","t":"p_0","w":0.394},{"s":"v15","t":"p_0","w":0.827},{"s":"v15","t":"p_0","w":0.615},{"s":"v15","t":"p_0","w":0.268},{"s":"v16","t":"p_0","w":0.941},{"s":"v16","t":"p_0","w":0.866},{"s":"v16","t":"p_0","w":0.44},{"s":"v16","t":"p_0","w":0.285},{"s":"v16","t":"p_0","w":0.281},{"s":"v17","t":"p_0","w":0.994},{"s":"v17","t":"p_0","w":0.503},{"s":"v17","t":"p_0","w":0.29},{"s":"v18","t":"p_0","w":0.886},{"s":"v18","t":"p_0","w":0.417},{"s":"v18","t":"p_0","w":0.414},{"s":"v18","t":"p_0","w":0.401},{"s":"v18","t":"p_0","w":0.395}]}