{"nodes":[{"id":"v1","t":"v","n":1,"x":"MY soul is weary of my life; I will leave my complaint upon myself; I will speak in the bitterness of my soul."},{"id":"v2","t":"v","n":2,"x":"I will say unto God, Do not condemn me; shew me wherefore thou contendest with me."},{"id":"p_0","t":"p","src":"jst","lb":"JST: inspired_version_1867","x":"2°I will say: unto God, Do not con- demn me; show me: wherefore thou contendest with me. :"},{"id":"v3","t":"v","n":3,"x":"[Is it] good unto thee that thou shouldest oppress, that thou shouldest despise the work of thine hands, and shine upon the counsel of the wicked?"},{"id":"v4","t":"v","n":4,"x":"Hast thou eyes of flesh? or seest thou as man seeth?"},{"id":"v5","t":"v","n":5,"x":"[Are] thy days as the days of man? [are] thy years as man's days,"},{"id":"p_1","t":"p","src":"sefaria","lb":"Second Temple: The Midrash of Philo 6:3:8-13","x":"Why it is said that the days of man shall be a hundred and twenty years? (Genesis 6:4)."},{"id":"v6","t":"v","n":6,"x":"That thou enquirest after mine iniquity, and searchest after my sin?"},{"id":"p_2","t":"p","src":"pseudepigrapha","lb":"Pseudepigrapha: charles_apot_vol2_pseudepigrapha","x":"Then I awoke °by reason of great perplexity of mind°® and from great fear, and said unto 4my spirit: Lo! this hast thou brought unto me because thou searchest out the ways of the Most High."},{"id":"v7","t":"v","n":7,"x":"Thou knowest that I am not wicked; and [there is] none that can deliver out of thine hand."},{"id":"p_3","t":"p","src":"apocrypha","lb":"LXX Apocrypha: charles_apot_vol1_apocrypha","x":"*Whom thou knowest to be a keeper of the Law’; *Whose heart is at one with thine own’,"},{"id":"v8","t":"v","n":8,"x":"Thine hands have made me and fashioned me together round about; yet thou dost destroy me."},{"id":"v9","t":"v","n":9,"x":"Remember, I beseech thee, that thou hast made me as the clay; and wilt thou bring me into dust again?"},{"id":"v10","t":"v","n":10,"x":"Hast thou not poured me out as milk, and curdled me like cheese?"},{"id":"v11","t":"v","n":11,"x":"Thou hast clothed me with skin and flesh, and hast fenced me with bones and sinews."},{"id":"v12","t":"v","n":12,"x":"Thou hast granted me life and favour, and thy visitation hath preserved my spirit."},{"id":"v13","t":"v","n":13,"x":"And these [things] hast thou hid in thine heart: I know that this [is] with thee."},{"id":"v14","t":"v","n":14,"x":"If I sin, then thou markest me, and thou wilt not acquit me from mine iniquity."},{"id":"v15","t":"v","n":15,"x":"If I be wicked, woe unto me; and [if] I be righteous, [yet] will I not lift up my head. [I am] full of confusion; therefore see thou mine affliction;"},{"id":"v16","t":"v","n":16,"x":"For it increaseth. Thou huntest me as a fierce lion: and again thou shewest thyself marvellous"},{"id":"v17","t":"v","n":17,"x":"Thou renewest thy witnesses against me, and increasest thine indignation upon me; changes and war [are] against me."},{"id":"v18","t":"v","n":18,"x":"Wherefore then hast thou brought me forth out of the womb? Oh that I had given up the ghost, and no eye had seen me!"},{"id":"v19","t":"v","n":19,"x":"I should have been as though I had not been; I should have been carried from the womb to the grave."},{"id":"v20","t":"v","n":20,"x":"[Are] not my days few? cease [then, and] let me alone, that I may take comfort a little,"},{"id":"v21","t":"v","n":21,"x":"Before I go [whence] I shall not return, [even] to the land of darkness and the shadow of death;"},{"id":"v22","t":"v","n":22,"x":"A land of darkness, as darkness [itself; and] of the shadow of death, without any order, and [where] the light [is] as darkness."},{"id":"p_4","t":"p","src":"donaldson","lb":"Donaldson on Job 10:14","x":"Job was \"full of confusion\" about whether he would be found wicked or righteous, wondering why he had been born and why he was still alive; he hoped only for a little respite before sinking permanently into \"a land of darkness, . . . and of the shadow of death, without any order, and where the light is as darkness\" (Job 10:14-22). (Ellis T. Rasmussen, A Latter-day Saint Commentary on the Old…"}],"edges":[{"s":"v2","t":"p_0","w":0.631},{"s":"v3","t":"p_0","w":0.94},{"s":"v3","t":"p_0","w":0.316},{"s":"v3","t":"p_0","w":0.311},{"s":"v3","t":"p_0","w":0.291},{"s":"v3","t":"p_0","w":0.264},{"s":"v4","t":"p_0","w":0.3},{"s":"v4","t":"p_0","w":0.286},{"s":"v5","t":"p_0","w":0.264},{"s":"v5","t":"p_1","w":0.252},{"s":"v6","t":"p_2","w":0.27},{"s":"v7","t":"p_0","w":0.304},{"s":"v7","t":"p_0","w":0.303},{"s":"v7","t":"p_0","w":0.297},{"s":"v7","t":"p_3","w":0.273},{"s":"v8","t":"p_0","w":1.0},{"s":"v9","t":"p_0","w":1.0},{"s":"v11","t":"p_0","w":0.964},{"s":"v12","t":"p_0","w":0.964},{"s":"v13","t":"p_0","w":0.933},{"s":"v14","t":"p_0","w":0.897},{"s":"v15","t":"p_0","w":0.948},{"s":"v16","t":"p_0","w":0.782},{"s":"v17","t":"p_0","w":0.967},{"s":"v18","t":"p_0","w":0.95},{"s":"v19","t":"p_0","w":0.845},{"s":"v19","t":"p_0","w":0.292},{"s":"v20","t":"p_0","w":0.912},{"s":"v21","t":"p_0","w":0.912},{"s":"v21","t":"p_0","w":0.555},{"s":"v21","t":"p_0","w":0.374},{"s":"v21","t":"p_0","w":0.348},{"s":"v21","t":"p_0","w":0.338},{"s":"v22","t":"p_0","w":0.928},{"s":"v22","t":"p_0","w":0.545},{"s":"v22","t":"p_4","w":0.441},{"s":"v22","t":"p_0","w":0.324},{"s":"v22","t":"p_0","w":0.312}]}